vision_parse/__init__.py
vision_parse/constants.py
vision_parse/llm.py
vision_parse/parser.py
vision_parse/utils.py
vision_parse/image_analysis.j2
vision_parse/markdown_prompt.j2
vision_parse-0.1.12.dist-info/METADATA
vision_parse-0.1.12.dist-info/WHEEL
vision_parse-0.1.12.dist-info/licenses/LICENSE
vision_parse-0.1.12.dist-info/RECORD
