Metadata-Version: 2.4
Name: vision-parse
Version: 0.1.12
Summary: Parse PDF documents into markdown formatted content using Vision LLMs
Project-URL: Homepage, https://github.com/iamarunbrahma/vision-parse
Project-URL: Repository, https://github.com/iamarunbrahma/vision-parse.git
Author-email: Arun Brahma <mithubrahma@gmail.com>
License-Expression: MIT
License-File: LICENSE
Keywords: document parser,markdown,ocr,pdf,pdf to markdown,vision llm
Classifier: Development Status :: 3 - Alpha
Classifier: Intended Audience :: Developers
Classifier: License :: OSI Approved :: MIT License
Classifier: Programming Language :: Python :: 3
Classifier: Programming Language :: Python :: 3.9
Classifier: Programming Language :: Python :: 3.10
Classifier: Programming Language :: Python :: 3.11
Classifier: Programming Language :: Python :: 3.12
Classifier: Programming Language :: Python :: 3.13
Requires-Python: >=3.9
Requires-Dist: jinja2>=3.0.0
Requires-Dist: nest-asyncio>=1.6.0
Requires-Dist: numpy>=2.0.0
Requires-Dist: ollama>=0.4.4
Requires-Dist: opencv-python>=4.10.0.84
Requires-Dist: pydantic>=2.0.0
Requires-Dist: pymupdf>=1.22.0
Requires-Dist: tenacity>=9.0.0
Requires-Dist: tqdm>=4.65.0
Provides-Extra: all
Requires-Dist: google-generativeai==0.8.3; extra == 'all'
Requires-Dist: openai==1.59.8; extra == 'all'
Provides-Extra: dev
Requires-Dist: black>=24.4.1; extra == 'dev'
Requires-Dist: black[jupyter]>=24.8.0; extra == 'dev'
Requires-Dist: build>=1.2.2; extra == 'dev'
Requires-Dist: pytest-asyncio>=0.23.5; extra == 'dev'
Requires-Dist: pytest>=8.3.4; extra == 'dev'
Requires-Dist: ruff>=0.8.3; extra == 'dev'
Requires-Dist: twine>=6.0.1; extra == 'dev'
Provides-Extra: gemini
Requires-Dist: google-generativeai==0.8.3; extra == 'gemini'
Provides-Extra: openai
Requires-Dist: openai==1.59.8; extra == 'openai'
